infi.winapi.file_version_information-0.0.11-py2.7-nspkg.pth
infi/winapi/file_version_information/__init__.py
infi/winapi/file_version_information/__version__.py
infi/winapi/file_version_information/api/__init__.py
infi/winapi/file_version_information/tests/__init__.py
infi.winapi.file_version_information-0.0.11.dist-info/LICENSE
infi.winapi.file_version_information-0.0.11.dist-info/METADATA
infi.winapi.file_version_information-0.0.11.dist-info/WHEEL
infi.winapi.file_version_information-0.0.11.dist-info/entry_points.txt
infi.winapi.file_version_information-0.0.11.dist-info/namespace_packages.txt
infi.winapi.file_version_information-0.0.11.dist-info/top_level.txt
infi.winapi.file_version_information-0.0.11.dist-info/RECORD
